vacuum_map_parser_base/__init__.py
vacuum_map_parser_base/config/__init__.py
vacuum_map_parser_base/config/color.py
vacuum_map_parser_base/config/drawable.py
vacuum_map_parser_base/config/image_config.py
vacuum_map_parser_base/config/size.py
vacuum_map_parser_base/config/text.py
vacuum_map_parser_base/image_generator.py
vacuum_map_parser_base/map_data.py
vacuum_map_parser_base/map_data_parser.py
vacuum_map_parser_base/py.typed
vacuum_map_parser_base-0.1.5.dist-info/LICENSE
vacuum_map_parser_base-0.1.5.dist-info/METADATA
vacuum_map_parser_base-0.1.5.dist-info/WHEEL
vacuum_map_parser_base-0.1.5.dist-info/RECORD
