Metadata-Version: 2.1
Name: vacuum-map-parser-base
Version: 0.1.5
Summary: Common code for vacuum map parsers
License: Apache-2.0
Author: Piotr Machowski
Author-email: piotr.machowski.dev@gmail.com
Requires-Python: >=3.11,<4.0
Classifier: Development Status :: 4 - Beta
Classifier: Environment :: Console
Classifier: Intended Audience :: Developers
Classifier: License :: OSI Approved :: Apache Software License
Classifier: Programming Language :: Python :: 3
Classifier: Programming Language :: Python :: 3.11
Classifier: Topic :: Home Automation
Requires-Dist: Pillow
Project-URL: Bug Tracker, https://github.com/PiotrMachowski/Python-package-vacuum-map-parser-base/issues
Project-URL: Changelog, https://github.com/PiotrMachowski/Python-package-vacuum-map-parser-base/releases
Project-URL: Homepage, https://github.com/PiotrMachowski/Python-package-vacuum-map-parser-base
Project-URL: Repository, https://github.com/PiotrMachowski/Python-package-vacuum-map-parser-base
